[
    {
        "from":     "box/:box/key/:key",
        "to":       "/_list/box/by_key",
        "method":   "GET",
        "query":    {
            "key":  [":box", ":key", false]
        }
    },
    {
        "from":     "box/:box/status/:status",
        "to":       "/_list/as-array/by_status",
        "method":   "GET",
        "query":    {
            "key":  [":box", ":status"]
        }
    },
    {
        "from":     "box/:box/key/:key",
        "to":       "/_update/timestamp",
        "method":   "POST",
        "query":    {
            "box":  ":box",
            "key":  ":key"
        }
    },
    {
        "from":     "meta/:box/key/:key",
        "to":       "/_list/as-array/by_key",
        "method":   "GET",
        "query":    {
            "key": [":box", ":key", true]
        }
    }
]
